kabbes_smart_documentation/CONFIG.json
kabbes_smart_documentation/Client.py
kabbes_smart_documentation/DocumentationGenerator.py
kabbes_smart_documentation/__init__.py
kabbes_smart_documentation/__main__.py
kabbes_smart_documentation/sphinx_script.sh
kabbes_smart_documentation/Templates/default/.github/workflows/kabbes_smart_documentation.yml
kabbes_smart_documentation/Templates/sphinx/Makefile
kabbes_smart_documentation/Templates/sphinx/conf.py
kabbes_smart_documentation/Templates/sphinx/index.rst
kabbes_smart_documentation/Templates/sphinx/make.bat
kabbes_smart_documentation-0.20.0.dist-info/LICENSE
kabbes_smart_documentation-0.20.0.dist-info/METADATA
kabbes_smart_documentation-0.20.0.dist-info/WHEEL
kabbes_smart_documentation-0.20.0.dist-info/top_level.txt
kabbes_smart_documentation-0.20.0.dist-info/RECORD
