Metadata-Version: 2.1
Name: kabbes-smart-documentation
Version: 0.20.0
Home-page: https://pypi.org/project/kabbes_smart_documentation
Author: James Kabbes
Author-email: james.kabbes@gmail.com
Project-URL: GitHub, https://github.com/jameskabbes/smart_documentation
Project-URL: Documentation, https://jameskabbes.github.io/smart_documentation
Classifier: Programming Language :: Python :: 3
Classifier: License :: OSI Approved :: MIT License
Classifier: Operating System :: OS Independent
Requires-Python: >=3.7
License-File: LICENSE
Requires-Dist: Sphinx
Requires-Dist: sphinx-rtd-theme
Requires-Dist: sphinx-autodoc-typehints
Requires-Dist: sphinxcontrib-applehelp
Requires-Dist: sphinxcontrib-devhelp
Requires-Dist: sphinxcontrib-htmlhelp
Requires-Dist: sphinxcontrib-jsmath
Requires-Dist: sphinxcontrib-qthelp
Requires-Dist: sphinxcontrib-serializinghtml
Requires-Dist: kabbes-client (>=0.2.0)
Requires-Dist: kabbes-config (>=0.1.0)
Requires-Dist: kabbes-pypi-builder (>=0.11.0)
Requires-Dist: kabbes-repository-generator (>=0.10.0)
Requires-Dist: kabbes-parent-class (>=0.5.0)
Requires-Dist: kabbes-dir-ops (>=0.7.0)
Requires-Dist: kabbes-py-starter (>=0.8.0)
